splight_runner/__init__.py
splight_runner/api/__init__.py
splight_runner/api/component_reporter.py
splight_runner/api/logging_interceptor.py
splight_runner/api/settings.py
splight_runner/bootstrap/__init__.py
splight_runner/bootstrap/sitecustomize.py
splight_runner/commands/__init__.py
splight_runner/commands/admin.py
splight_runner/commands/execute_agent.py
splight_runner/commands/execute_component.py
splight_runner/config.py
splight_runner/hooks/__init__.py
splight_runner/hooks/constants.py
splight_runner/hooks/finder.py
splight_runner/hooks/loader.py
splight_runner/hooks/meta_paths.py
splight_runner/hooks/registry.py
splight_runner/hooks/utils.py
splight_runner/log_streamer/__init__.py
splight_runner/log_streamer/log_buffer.py
splight_runner/log_streamer/log_client.py
splight_runner/log_streamer/log_streamer.py
splight_runner/logging.py
splight_runner/runner.py
splight_runner/version.py
splight_runner/wrapper/__init__.py
splight_runner/wrapper/healthcheck.py
splight_runner/wrapper/hooks.py
splight_runner/wrapper/logging.py
splight_runner-1.1.2.dist-info/METADATA
splight_runner-1.1.2.dist-info/WHEEL
splight_runner-1.1.2.dist-info/entry_points.txt
splight_runner-1.1.2.dist-info/RECORD
